[
  {
    "id": "1",
    "question": {
      "value": "您平常會如何響應走塑行動？",
      "label": "您平常會如何響應走塑行動？"
    },
    "content": {
      "value": "",
      "label": "最多選取3項<br/><br/><small>提提大家：解決塑膠污染問題，源頭減廢方為上策，回收只屬最後防線，要將美麗健康的環境留給下一代，長遠之道必須由源頭減廢開始做起！</small>"
    },
    "options": [
      { "value": "1", "label": "避免使用即棄塑膠包裝" },
      {
        "value": "2",
        "label": "自行攜帶可重複使用的餐具、容器"
      },
      { "value": "3", "label": "參與回收" },
      {
        "value": "4",
        "label": "參與淨山、淨灘、淨海相關活動"
      },
      {
        "value": "5",
        "label": "嘗試各種減塑創新方法，如租借可重用餐具、光顧裸買店"
      }
    ],
    "maximum": 3,
    "type": "multiple"
  },
  {
    "id": "2",
    "question": {
      "value": "您認為最難避免使用的塑膠製品是？",
      "label": "您認為最難避免使用的塑膠製品是？"
    },
    "content": { "value": "", "label": "最多選取3項" },
    "options": [
      { "value": "1", "label": "背心膠袋" },
      {
        "value": "2",
        "label": "即棄餐具（飲管、膠杯...）"
      },
      { "value": "3", "label": "蔬果即棄塑膠包裝" },
      { "value": "4", "label": "護理用品膠樽" },
      { "value": "5", "label": "食品、飲品包裝" }
    ],
    "maximum": 3,
    "type": "multiple"
  },
  {
    "id": "3",
    "question": {
      "value": "您認為響應走塑的難處是？",
      "label": "您認為響應走塑的難處是？"
    },
    "content": { "value": "", "label": "最多選取3項" },
    "options": [
      { "value": "1", "label": "欠缺整全政策支持" },
      { "value": "2", "label": "商品已預先包上塑膠包裝" },
      { "value": "3", "label": "社區走塑配套不足" },
      { "value": "4", "label": "店鋪未能配合提供走塑選擇" },
      { "value": "5", "label": "個人習慣" }
    ],
    "maximum": 3,
    "type": "multiple"
  },
  {
    "id": "4",
    "question": {
      "value": "如塑膠污染持續惡化，您認為人類與環境將面臨以下哪項危機？",
      "label": "如塑膠污染持續惡化，您認為人類與環境將面臨以下哪項危機？"
    },
    "content": { "value": "", "label": "最多選取3項" },
    "options": [
      {
        "value": "1",
        "label": "污染自然生態（山野、海洋）"
      },
      {
        "value": "2",
        "label": "威脅海洋生物生存（誤食、被塑膠垃圾纏繞）"
      },
      { "value": "3", "label": "破壞下一代的生態環境" },
      { "value": "4", "label": "加重堆填區負擔" },
      {
        "value": "5",
        "label": "微塑膠入侵食物鏈，危害健康"
      }
    ],
    "maximum": 3,
    "type": "multiple"
  },
  {
    "id": "5",
    "question": {
      "value": "您認為以下哪一項措施，最能從根源解決塑膠污染問題？",
      "label": "您認為以下哪一項措施，最能從根源解決塑膠污染問題？"
    },
    "content": { "value": "", "label": "最多選取1項" },
    "options": [
      {
        "value": "1",
        "label": "加強市民對減塑的意識與關注，帶動社會減塑風潮"
      },
      {
        "value": "2",
        "label": "連結全港各社區店鋪，為市民提供無包裝貨品或走塑優惠"
      },
      {
        "value": "3",
        "label": "要求企業如超市、連鎖快餐店等淘汰即棄塑膠包裝或器皿，為消費者提供無塑選擇 "
      },
      {
        "value": "4",
        "label": "政府加強源頭減廢政策，例如提前於2025年管制即棄膠餐具"
      },
      { "value": "5", "label": "其他：請注明" }
    ],
    "maximum": 1,
    "type": "single"
  }
]
